mcp_redmine/__init__.py
mcp_redmine/redmine_openapi.yml
mcp_redmine/server.py
mcp_redmine-2026.1.13.152335.dist-info/METADATA
mcp_redmine-2026.1.13.152335.dist-info/WHEEL
mcp_redmine-2026.1.13.152335.dist-info/entry_points.txt
mcp_redmine-2026.1.13.152335.dist-info/licenses/LICENSE
mcp_redmine-2026.1.13.152335.dist-info/RECORD
