Metadata-Version: 2.4
Name: mcp-redmine
Version: 2026.1.13.152335
Summary: A MCP server that connects to your Redmine instance
Project-URL: Homepage, https://github.com/runekaagaard/mcp-redmine
Project-URL: Issues, https://github.com/runekaagaard/mcp-redmine/issues
Project-URL: Disussions, https://github.com/runekaagaard/mcp-redmine/discussions
Author: Rune Kaagaard
License-File: LICENSE
Classifier: Operating System :: OS Independent
Classifier: Programming Language :: Python :: 3
Requires-Python: >=3.10
Requires-Dist: httpx>=0.28.1
Requires-Dist: mcp[cli]>=1.9.0
Requires-Dist: openapi-core>=0.19.4
Requires-Dist: pyyaml>=6.0.2
